PYT_Metadata/__init__.py
PYT_Metadata/__main__.py
PYT_Metadata/generate_pyt_meta.py
pyt_metadata-1.1.1.dist-info/LICENSE
pyt_metadata-1.1.1.dist-info/WHEEL
pyt_metadata-1.1.1.dist-info/METADATA
pyt_metadata-1.1.1.dist-info/RECORD
