Metadata-Version: 2.1
Name: pyt-metadata
Version: 1.1.1
Summary: Metadata generator from python toolboxes
License: MIT
Author: Cody Scott
Author-email: jcodyscott+PYTMETA@gmail.com
Requires-Python: >=3.6,<4.0
Classifier: License :: OSI Approved :: MIT License
Classifier: Programming Language :: Python :: 3
Classifier: Programming Language :: Python :: 3.10
Classifier: Programming Language :: Python :: 3.6
Classifier: Programming Language :: Python :: 3.7
Classifier: Programming Language :: Python :: 3.8
Classifier: Programming Language :: Python :: 3.9
Requires-Dist: Jinja2 (>=3.0.3,<4.0.0)
Requires-Dist: Markdown (>=3.3.6,<4.0.0)
